milkyway_sdk/__init__.py
milkyway_sdk/async_utils.py
milkyway_sdk/cw721_base.wasm
milkyway_sdk/lcd_client.py
milkyway_sdk/minter.py
milkyway_sdk/terra_utils.py
milkyway_sdk-0.1.3.dist-info/WHEEL
milkyway_sdk-0.1.3.dist-info/METADATA
milkyway_sdk-0.1.3.dist-info/RECORD
